damster/VERSION
damster/__init__.py
damster/bam_builds_report.py
damster/bam_deployment_permissions_report.py
damster/bam_deployments_report.py
damster/cli.py
damster/metric.py
damster/utils.py
damster/metrics/__init__.py
damster/metrics/bamboo/__init__.py
damster/metrics/bamboo/agents.py
damster/reports/__init__.py
damster/reports/base_report.py
damster/reports/db_query.py
damster/reports/bamboo/__init__.py
damster/reports/bamboo/builds.py
damster/reports/bamboo/db_deployment_permissions.py
damster/reports/bamboo/deployments.py
damster/reports/bamboo/utils.py
damster/reports/confluence/__init__.py
damster/reports/confluence/db_changes.py
damster-0.2.1.dist-info/METADATA
damster-0.2.1.dist-info/RECORD
damster-0.2.1.dist-info/WHEEL
damster-0.2.1.dist-info/entry_points.txt
damster-0.2.1.dist-info/top_level.txt
tests/__init__.py
tests/test_bamboo_utils.py
tests/test_dummy.py
