Metadata-Version: 2.1
Name: damster
Version: 0.2.1
Summary: Reports and metrics for Atlassian Tools
Home-page: UNKNOWN
Author: Xabier Davila
Author-email: davila.xabier@gmail.com
License: Apache License 2.0
Download-URL: https://github.com/cattz/damster
Platform: Platform Independent
Classifier: Development Status :: 4 - Beta
Classifier: Environment :: Web Environment
Classifier: Intended Audience :: Developers
Classifier: Intended Audience :: System Administrators
Classifier: License :: OSI Approved :: Apache Software License
Classifier: Natural Language :: English
Classifier: Operating System :: OS Independent
Classifier: Operating System :: POSIX
Classifier: Operating System :: MacOS :: MacOS X
Classifier: Operating System :: Microsoft :: Windows
Classifier: Programming Language :: Python
Classifier: Programming Language :: Python :: 3.2
Classifier: Programming Language :: Python :: 3.3
Classifier: Programming Language :: Python :: 3.4
Classifier: Programming Language :: Python :: 3.5
Classifier: Programming Language :: Python :: 3.6
Classifier: Topic :: Software Development :: Libraries :: Python Modules
Classifier: Topic :: Software Development :: Libraries :: Application Frameworks
Provides-Extra: dev
Requires-Dist: configparser
Requires-Dist: arrow
Requires-Dist: click
Requires-Dist: atlassian-python-api
Requires-Dist: arrow
Requires-Dist: influxdb
Requires-Dist: schedule
Requires-Dist: jinja2
Requires-Dist: psycopg2
Requires-Dist: sshtunnel
Requires-Dist: six
Provides-Extra: dev
Requires-Dist: pytest; extra == 'dev'
Requires-Dist: pytest-pep8; extra == 'dev'
Requires-Dist: coverage; extra == 'dev'
Requires-Dist: tox; extra == 'dev'
